eudract/__init__.py
eudract/main.py
eudract/utils.py
eudract_py-1.3.0.dist-info/LICENSE
eudract_py-1.3.0.dist-info/METADATA
eudract_py-1.3.0.dist-info/WHEEL
eudract_py-1.3.0.dist-info/top_level.txt
eudract_py-1.3.0.dist-info/RECORD
