Metadata-Version: 2.1
Name: eudract-py
Version: 1.3.0
Summary: Eudract-py is a Python library for searching clinical trials on EUDRACT
Home-page: http://github.com/PaulinCharliquart/eudract-py
Author: Paulin Charliquart
Author-email: paulincharliquart@gmail.com
License: MIT
Project-URL: Bug Tracker, https://github.com/PaulinCharliquart/eudract-py/issues
Classifier: License :: OSI Approved :: MIT License
Classifier: Topic :: Scientific/Engineering :: Bio-Informatics
Classifier: Intended Audience :: Science/Research
Classifier: Operating System :: OS Independent
Classifier: Intended Audience :: Healthcare Industry
Classifier: Topic :: Scientific/Engineering
Classifier: Programming Language :: Python :: 3
License-File: LICENSE
Requires-Dist: requests
Requires-Dist: bs4
Provides-Extra: dev
Requires-Dist: black ; extra == 'dev'
Requires-Dist: pytest ; extra == 'dev'
Requires-Dist: flake8 ; extra == 'dev'
Requires-Dist: furo ; extra == 'dev'
Requires-Dist: sphinx ; extra == 'dev'
Requires-Dist: myst-parser ; extra == 'dev'
Requires-Dist: sphinx-copybutton ; extra == 'dev'
